MANIFEST.in
README.rst
setup.py
job_runner_worker/__init__.py
job_runner_worker/auth.py
job_runner_worker/cleanup.py
job_runner_worker/config.py
job_runner_worker/enqueuer.py
job_runner_worker/events.py
job_runner_worker/models.py
job_runner_worker/runner.py
job_runner_worker/worker.py
job_runner_worker.egg-info/PKG-INFO
job_runner_worker.egg-info/SOURCES.txt
job_runner_worker.egg-info/dependency_links.txt
job_runner_worker.egg-info/requires.txt
job_runner_worker.egg-info/top_level.txt
scripts/job_runner_worker