Metadata-Version: 1.0
Name: job-runner-worker
Version: 2.1.2
Summary: Job-Runner Worker
Home-page: https://github.com/spilgames/job-runner-worker/
Author: Orne Brocaar
Author-email: datawarehouse@spilgames.com
License: BSD
Platform: UNKNOWN
